sellpath_test/__init__.py
sellpath_test/client_mgr.py
sellpath_test/http_client.py
sellpath_test/sftest.py
sellpath_test/weather_demo_example.py
sellpath_test-0.0.34.dist-info/METADATA
sellpath_test-0.0.34.dist-info/WHEEL
sellpath_test-0.0.34.dist-info/top_level.txt
sellpath_test-0.0.34.dist-info/RECORD
