Metadata-Version: 2.1
Name: sellpath-test
Version: 0.0.34
Summary: test_description
Author: bigbowltakestime
Author-email: bigbowltakestime@gmail.com
Keywords: sellpath,sellpath_test
Classifier: Programming Language :: Python :: 3.11
Requires-Python: >=3.11
Requires-Dist: simple-salesforce
Requires-Dist: apollo
Requires-Dist: prefect
Requires-Dist: cryptography
Requires-Dist: shortuuid
Requires-Dist: hubspot-api-client
Requires-Dist: openai
